livestock_generation/__init__.py
livestock_generation/database/__init__.py
livestock_generation/database/livestock_database.db
livestock_generation/geo_livestock_generation/__init__.py
livestock_generation/geo_livestock_generation/geo_livestock.py
livestock_generation/geo_livestock_generation/geo_livestock_exports.py
livestock_generation/livestock.py
livestock_generation/livestock_exports.py
livestock_generation/resource_manager/__init__.py
livestock_generation/resource_manager/data_loader.py
livestock_generation/resource_manager/database_manager.py
livestock_generation/resource_manager/livestock_data_manager.py
livestock_generation/resource_manager/scenario_fetcher.py
livestock_generation-0.2.2.dist-info/LICENSE
livestock_generation-0.2.2.dist-info/METADATA
livestock_generation-0.2.2.dist-info/WHEEL
livestock_generation-0.2.2.dist-info/RECORD
